nautobot_secrets_providers/__init__.py
nautobot_secrets_providers/app-config-schema.json
nautobot_secrets_providers/migrations/0001_update_thycotic_delinea_slug.py
nautobot_secrets_providers/migrations/__init__.py
nautobot_secrets_providers/providers/__init__.py
nautobot_secrets_providers/providers/aws.py
nautobot_secrets_providers/providers/azure.py
nautobot_secrets_providers/providers/choices.py
nautobot_secrets_providers/providers/delinea.py
nautobot_secrets_providers/providers/hashicorp.py
nautobot_secrets_providers/providers/one_password.py
nautobot_secrets_providers/secrets.py
nautobot_secrets_providers/static/nautobot_secrets_providers/docs/404.html
nautobot_secrets_providers/static/nautobot_secrets_providers/docs/admin/compatibility_matrix.html
nautobot_secrets_providers/static/nautobot_secrets_providers/docs/admin/install.html
nautobot_secrets_providers/static/nautobot_secrets_providers/docs/admin/providers/aws_setup.html
nautobot_secrets_providers/static/nautobot_secrets_providers/docs/admin/providers/azure_setup.html
nautobot_secrets_providers/static/nautobot_secrets_providers/docs/admin/providers/delinea_setup.html
nautobot_secrets_providers/static/nautobot_secrets_providers/docs/admin/providers/hashicorp_setup.html
nautobot_secrets_providers/static/nautobot_secrets_providers/docs/admin/providers/index.html
nautobot_secrets_providers/static/nautobot_secrets_providers/docs/admin/providers/onepassword_setup.html
nautobot_secrets_providers/static/nautobot_secrets_providers/docs/admin/release_notes/index.html
nautobot_secrets_providers/static/nautobot_secrets_providers/docs/admin/release_notes/version_1.0.html
nautobot_secrets_providers/static/nautobot_secrets_providers/docs/admin/release_notes/version_1.1.html
nautobot_secrets_providers/static/nautobot_secrets_providers/docs/admin/release_notes/version_1.2.html
nautobot_secrets_providers/static/nautobot_secrets_providers/docs/admin/release_notes/version_1.3.html
nautobot_secrets_providers-4.0.0.dist-info/LICENSE
nautobot_secrets_providers-4.0.0.dist-info/METADATA
nautobot_secrets_providers-4.0.0.dist-info/WHEEL
nautobot_secrets_providers-4.0.0.dist-info/RECORD
