Metadata-Version: 2.3
Name: nautobot-secrets-providers
Version: 4.0.0
Summary: Nautobot Secrets Providers App
License: Apache-2.0
Keywords: nautobot,nautobot-app,nautobot-plugin
Author: Network to Code, LLC
Author-email: info@networktocode.com
Requires-Python: >=3.10,<3.14
Classifier: Development Status :: 5 - Production/Stable
Classifier: Intended Audience :: Developers
Classifier: License :: OSI Approved :: Apache Software License
Classifier: Programming Language :: Python :: 3
Classifier: Programming Language :: Python :: 3.10
Classifier: Programming Language :: Python :: 3.11
Classifier: Programming Language :: Python :: 3.12
Classifier: Programming Language :: Python :: 3.13
Provides-Extra: all
Provides-Extra: aws
Provides-Extra: azure
Provides-Extra: hashicorp
Provides-Extra: onepassword
Provides-Extra: thycotic
Requires-Dist: azure-identity (>=1.15.0,<2.0.0) ; extra == "all" or extra == "azure"
Requires-Dist: azure-keyvault-secrets (>=4.8.0,<5.0.0) ; extra == "all" or extra == "azure"
Requires-Dist: boto3 (>=1.19.5,<2.0.0) ; extra == "all" or extra == "aws"
Requires-Dist: hvac (>=0.11.0,<1.1.0) ; extra == "all" or extra == "hashicorp"
Requires-Dist: nautobot (>=3.0.0,<4.0.0)
Requires-Dist: onepassword-sdk (>=0.1.2,<0.2.0) ; (python_version >= "3.9") and (extra == "all" or extra == "onepassword")
Requires-Dist: python-tss-sdk (>=1.2.0,<1.3.0) ; extra == "all" or extra == "thycotic"
Project-URL: Documentation, https://docs.nautobot.com/projects/secrets-providers/en/latest/
Project-URL: Homepage, https://github.com/nautobot/nautobot-app-secrets-providers
Project-URL: Repository, https://github.com/nautobot/nautobot-app-secrets-providers
